{
	"info": {
		"_postman_id": "07cb0791-4223-45ff-9bdb-acae1ad8150b",
		"name": "olivas-crud",
		"schema": "https://schema.getpostman.com/json/collection/v2.1.0/collection.json"
	},
	"item": [
		{
			"name": "Auth",
			"item": [
				{
					"name": "auth.register",
					"request": {
						"method": "POST",
						"header": [
							{
								"key": "Accept",
								"value": "application/json",
								"type": "text"
							}
						],
						"body": {
							"mode": "raw",
							"raw": "{\r\n    \"name\": \"New User\",\r\n    \"email\": \"user1@gmail.com\",\r\n    \"password\": \"secret\",\r\n    \"password_confirmation\": \"secret\"\r\n}",
							"options": {
								"raw": {
									"language": "json"
								}
							}
						},
						"url": {
							"raw": "{{base_url}}/auth/register",
							"host": [
								"{{base_url}}"
							],
							"path": [
								"auth",
								"register"
							]
						}
					},
					"response": []
				},
				{
					"name": "auth.login",
					"request": {
						"method": "POST",
						"header": [
							{
								"key": "Accept",
								"value": "application/json",
								"type": "text"
							}
						],
						"body": {
							"mode": "raw",
							"raw": "{\r\n    \"email\": \"kevinalcantara37@gmail.com\",\r\n    \"password\": \"secret\"\r\n}",
							"options": {
								"raw": {
									"language": "json"
								}
							}
						},
						"url": {
							"raw": "{{base_url}}/auth/login",
							"host": [
								"{{base_url}}"
							],
							"path": [
								"auth",
								"login"
							]
						}
					},
					"response": []
				},
				{
					"name": "auth.logout",
					"request": {
						"method": "POST",
						"header": [
							{
								"key": "Accept",
								"value": "application/json",
								"type": "text"
							}
						],
						"url": {
							"raw": "{{base_url}}/auth/logout",
							"host": [
								"{{base_url}}"
							],
							"path": [
								"auth",
								"logout"
							]
						}
					},
					"response": []
				}
			]
		},
		{
			"name": "Clients",
			"item": [
				{
					"name": "clients.index",
					"request": {
						"method": "GET",
						"header": [
							{
								"key": "Accept",
								"value": "application/json",
								"type": "text"
							}
						],
						"url": {
							"raw": "{{base_url}}/clients",
							"host": [
								"{{base_url}}"
							],
							"path": [
								"clients"
							]
						}
					},
					"response": []
				},
				{
					"name": "clients.show",
					"request": {
						"method": "GET",
						"header": [
							{
								"key": "Accept",
								"value": "application/json",
								"type": "text"
							}
						],
						"url": {
							"raw": "{{base_url}}/clients/1",
							"host": [
								"{{base_url}}"
							],
							"path": [
								"clients",
								"1"
							]
						}
					},
					"response": []
				},
				{
					"name": "clients.store",
					"request": {
						"method": "POST",
						"header": [
							{
								"key": "Accept",
								"value": "application/json",
								"type": "text"
							}
						],
						"body": {
							"mode": "raw",
							"raw": "{\r\n    \"name\": \"New Client\",\r\n    \"email\": \"keuvin@gmail.com\",\r\n    \"client_type_id\": 1,\r\n    \"phones\": [\r\n        {\r\n            \"number\": \"18 99806-5368\"\r\n        },\r\n        {\r\n            \"number\": \"81 97807-5388\"\r\n        }\r\n    ],\r\n    \"sellers\": [\r\n        {\r\n            \"id\": 1\r\n        },\r\n        {\r\n            \"id\": 5\r\n        },\r\n        {\r\n            \"id\": 3\r\n        }\r\n    ]\r\n}",
							"options": {
								"raw": {
									"language": "json"
								}
							}
						},
						"url": {
							"raw": "{{base_url}}/clients",
							"host": [
								"{{base_url}}"
							],
							"path": [
								"clients"
							]
						}
					},
					"response": []
				},
				{
					"name": "clients.update",
					"request": {
						"method": "PUT",
						"header": [
							{
								"key": "Accept",
								"value": "application/json",
								"type": "text"
							}
						],
						"body": {
							"mode": "raw",
							"raw": "{\r\n    \"name\": \"Client Updated\",\r\n    \"client_type_id\": 1,\r\n    \"phones\": [\r\n        {\r\n            \"number\": \"18 99745-5368\"\r\n        }\r\n    ],\r\n    \"sellers\": [\r\n        {\r\n            \"id\": 8\r\n        }\r\n    ]\r\n}",
							"options": {
								"raw": {
									"language": "json"
								}
							}
						},
						"url": {
							"raw": "{{base_url}}/clients/1",
							"host": [
								"{{base_url}}"
							],
							"path": [
								"clients",
								"1"
							]
						}
					},
					"response": []
				},
				{
					"name": "clients.destroy",
					"request": {
						"method": "DELETE",
						"header": [
							{
								"key": "Accept",
								"value": "application/json",
								"type": "text"
							}
						],
						"url": {
							"raw": "{{base_url}}/clients/1",
							"host": [
								"{{base_url}}"
							],
							"path": [
								"clients",
								"1"
							]
						}
					},
					"response": []
				}
			]
		},
		{
			"name": "Sellers",
			"item": [
				{
					"name": "sellers.index",
					"request": {
						"method": "GET",
						"header": [
							{
								"key": "Accept",
								"value": "application/json",
								"type": "text"
							}
						],
						"url": {
							"raw": "{{base_url}}/sellers",
							"host": [
								"{{base_url}}"
							],
							"path": [
								"sellers"
							]
						}
					},
					"response": []
				},
				{
					"name": "sellers.show",
					"request": {
						"method": "GET",
						"header": [
							{
								"key": "Accept",
								"value": "application/json",
								"type": "text"
							}
						],
						"url": {
							"raw": "{{base_url}}/sellers/1",
							"host": [
								"{{base_url}}"
							],
							"path": [
								"sellers",
								"1"
							]
						}
					},
					"response": []
				},
				{
					"name": "sellers.store",
					"request": {
						"method": "POST",
						"header": [
							{
								"key": "Accept",
								"value": "application/json",
								"type": "text"
							}
						],
						"body": {
							"mode": "raw",
							"raw": "{\r\n    \"name\": \"New Seller\",\r\n    \"email\": \"kevin@gmail.com\",\r\n    \"clients\": [\r\n        {\r\n            \"id\": 1\r\n        },\r\n        {\r\n            \"id\": 5\r\n        },\r\n        {\r\n            \"id\": 3\r\n        }\r\n    ]\r\n}",
							"options": {
								"raw": {
									"language": "json"
								}
							}
						},
						"url": {
							"raw": "{{base_url}}/sellers",
							"host": [
								"{{base_url}}"
							],
							"path": [
								"sellers"
							]
						}
					},
					"response": []
				},
				{
					"name": "sellers.update",
					"request": {
						"method": "PUT",
						"header": [
							{
								"key": "Accept",
								"value": "application/json",
								"type": "text"
							}
						],
						"body": {
							"mode": "raw",
							"raw": "{\r\n    \"name\": \"Seller Updated\",\r\n    \"clients\": [\r\n        {\r\n            \"id\": 8\r\n        }\r\n    ]\r\n}",
							"options": {
								"raw": {
									"language": "json"
								}
							}
						},
						"url": {
							"raw": "{{base_url}}/sellers/1",
							"host": [
								"{{base_url}}"
							],
							"path": [
								"sellers",
								"1"
							]
						}
					},
					"response": []
				},
				{
					"name": "sellers.destroy",
					"request": {
						"method": "DELETE",
						"header": [
							{
								"key": "Accept",
								"value": "application/json",
								"type": "text"
							}
						],
						"url": {
							"raw": "{{base_url}}/sellers/1",
							"host": [
								"{{base_url}}"
							],
							"path": [
								"sellers",
								"1"
							]
						}
					},
					"response": []
				}
			]
		}
	],
	"auth": {
		"type": "bearer",
		"bearer": [
			{
				"key": "token",
				"value": "eyJ0eXAiOiJKV1QiLCJhbGciOiJIUzI1NiJ9.eyJpc3MiOiJodHRwOlwvXC9sb2NhbGhvc3Q6ODAwMFwvYXBpXC9hdXRoXC9sb2dpbiIsImlhdCI6MTY1MTA4OTMwNCwiZXhwIjoxNjUxMDkyOTA0LCJuYmYiOjE2NTEwODkzMDQsImp0aSI6Ik5KazBUOU1HdFhydG80S2MiLCJzdWIiOjEsInBydiI6IjIzYmQ1Yzg5NDlmNjAwYWRiMzllNzAxYzQwMDg3MmRiN2E1OTc2ZjcifQ.glJPAJs8UjRY21K6fPDnSTAYCfREeY681HsxSAvFGvU",
				"type": "string"
			}
		]
	},
	"event": [
		{
			"listen": "prerequest",
			"script": {
				"type": "text/javascript",
				"exec": [
					""
				]
			}
		},
		{
			"listen": "test",
			"script": {
				"type": "text/javascript",
				"exec": [
					""
				]
			}
		}
	],
	"variable": [
		{
			"key": "base_url",
			"value": "http://localhost:8000/api",
			"type": "string"
		}
	]
}